odoo/addons/account_invoice_tree_currency/README.rst
odoo/addons/account_invoice_tree_currency/__init__.py
odoo/addons/account_invoice_tree_currency/__manifest__.py
odoo/addons/account_invoice_tree_currency/i18n/account_invoice_tree_currency.pot
odoo/addons/account_invoice_tree_currency/i18n/ca.po
odoo/addons/account_invoice_tree_currency/i18n/es.po
odoo/addons/account_invoice_tree_currency/i18n/it.po
odoo/addons/account_invoice_tree_currency/readme/CONTRIBUTORS.rst
odoo/addons/account_invoice_tree_currency/readme/DESCRIPTION.rst
odoo/addons/account_invoice_tree_currency/static/description/icon.png
odoo/addons/account_invoice_tree_currency/static/description/index.html
odoo/addons/account_invoice_tree_currency/views/account_move_view.xml
odoo14_addon_account_invoice_tree_currency-14.0.1.0.1.dev9.dist-info/METADATA
odoo14_addon_account_invoice_tree_currency-14.0.1.0.1.dev9.dist-info/WHEEL
odoo14_addon_account_invoice_tree_currency-14.0.1.0.1.dev9.dist-info/top_level.txt
odoo14_addon_account_invoice_tree_currency-14.0.1.0.1.dev9.dist-info/RECORD
